<?xml version="1.0" encoding="UTF-8"?>

<arbolesTropicales>
    <nombre>Litchi</nombre>
    <variedad>Kway may pink</variedad>
    <origen>Filipinas</origen>
    <colorFruto>Rosa</colorFruto>
    <maduracion>Agosto</maduracion>
    <riego>diario</riego>
    <precio moneda="euro" peso="kg">3,5</precio>
    
    <nombre>Logan</nombre>
    <variedad>Champoo</variedad>
    <origen>China</origen>
    <colorFruto>Marrón</colorFruto>
    <maduracion>Octubre</maduracion>
    <riego>diario</riego>
    <precio moneda="euro" peso="kg">2,5</precio>
    
    <nombre>Litchi</nombre>
    <variedad>Mauritius</variedad>
    <origen>Florida</origen>
    <colorFruto>Rojo</colorFruto>
    <maduracion>Agosto</maduracion>
    <riego>diario</riego>
    <precio moneda="euro" peso="kg">3</precio>
</arbolesTropicales>
